{"GlobalPropertiesHash":"2ilJ2M8+ZdH0swl4cXFj9Ji8kay0R08ISE/fEc+OL0o=","FingerprintPatternsHash":"8ZRc1sGeVrPBx4lD717BgRaQekyh78QKV9SKsdt638U=","PropertyOverridesHash":"8ZRc1sGeVrPBx4lD717BgRaQekyh78QKV9SKsdt638U=","InputHashes":["V2ewg/VrxTm3AM5f6YOx5tETq0Mwc2ryBR0JquXkWtI=","6CStaJAhZaNssdeuB5T0GtokEpEZaD8VtEGVWpgI/Ts="],"CachedAssets":{"6CStaJAhZaNssdeuB5T0GtokEpEZaD8VtEGVWpgI/Ts=":{"Identity":"D:\\Desktop\\test-SSP\\SSP_v4\\LoopVisualizerSystem\\obj\\Debug\\net9.0\\compressed\\lz95sj91fw-3sxjxkuk9a.gz","SourceId":"LoopVisualizerSystem","SourceType":"Discovered","ContentRoot":"D:\\Desktop\\test-SSP\\SSP_v4\\LoopVisualizerSystem\\obj\\Debug\\net9.0\\compressed\\","BasePath":"_content/LoopVisualizerSystem","RelativePath":"app#[.{fingerprint=3sxjxkuk9a}]?.js.gz","AssetKind":"All","AssetMode":"All","AssetRole":"Alternative","AssetMergeBehavior":null,"AssetMergeSource":"","RelatedAsset":"D:\\Desktop\\test-SSP\\SSP_v4\\LoopVisualizerSystem\\wwwroot\\app.js","AssetTraitName":"Content-Encoding","AssetTraitValue":"gzip","Fingerprint":"xdl8r5tbcu","Integrity":"Rd00SisE\u002BQJv4mbNS/SvQMfIG\u002B2Olfr1vcM7gUX\u002Bz3A=","CopyToOutputDirectory":"Never","CopyToPublishDirectory":"PreserveNewest","OriginalItemSpec":"D:\\Desktop\\test-SSP\\SSP_v4\\LoopVisualizerSystem\\wwwroot\\app.js","FileLength":25765,"LastWriteTime":"2026-06-16T01:33:34.4947355+00:00"},"V2ewg/VrxTm3AM5f6YOx5tETq0Mwc2ryBR0JquXkWtI=":{"Identity":"D:\\Desktop\\test-SSP\\SSP_v4\\LoopVisualizerSystem\\obj\\Debug\\net9.0\\compressed\\8qewn01zbz-snxjh7mmd3.gz","SourceId":"LoopVisualizerSystem","SourceType":"Discovered","ContentRoot":"D:\\Desktop\\test-SSP\\SSP_v4\\LoopVisualizerSystem\\obj\\Debug\\net9.0\\compressed\\","BasePath":"_content/LoopVisualizerSystem","RelativePath":"index#[.{fingerprint=snxjh7mmd3}]?.html.gz","AssetKind":"All","AssetMode":"All","AssetRole":"Alternative","AssetMergeBehavior":null,"AssetMergeSource":"","RelatedAsset":"D:\\Desktop\\test-SSP\\SSP_v4\\LoopVisualizerSystem\\wwwroot\\index.html","AssetTraitName":"Content-Encoding","AssetTraitValue":"gzip","Fingerprint":"n9d27k11c8","Integrity":"qzYzIrVGvLdaBnju8EM2GiQH4zs\u002BTbAapIK5wSHY5ws=","CopyToOutputDirectory":"Never","CopyToPublishDirectory":"PreserveNewest","OriginalItemSpec":"D:\\Desktop\\test-SSP\\SSP_v4\\LoopVisualizerSystem\\wwwroot\\index.html","FileLength":4998,"LastWriteTime":"2026-06-16T01:29:33.704746+00:00"}},"CachedCopyCandidates":{}}